{"orderbooks":[{"baseAsset":"TATA","bids":[{"price":997.19,"quantity":2.13,"orderId":"ffeq2ut04fovvxniptv2fj","filled":0,"side":"buy","userId":"5"},{"price":997.44,"quantity":1.57,"orderId":"xhacq9kwzzxyv23o9coad","filled":0,"side":"buy","userId":"5"},{"price":1000.64,"quantity":2.48,"orderId":"8ziepllo8kab00kkfzqzn","filled":0,"side":"buy","userId":"5"},{"price":1004.98,"quantity":2.35,"orderId":"4pezq6opmc4t28h9ee79qh","filled":0,"side":"buy","userId":"5"},{"price":1005.41,"quantity":2.72,"orderId":"o8j33qbjmfeci95raata0j","filled":0,"side":"buy","userId":"5"},{"price":1005.58,"quantity":1.11,"orderId":"ppbwbqkmhbtihw0dsmq9q","filled":0.010000000000000231,"side":"buy","userId":"5"},{"price":1005.7,"quantity":0.74,"orderId":"2gyaw16q2j9qxtrrtzc44h","filled":0,"side":"buy","userId":"5"},{"price":1005.81,"quantity":1.4,"orderId":"tqz7me28vfjzqnajybau9d","filled":0,"side":"buy","userId":"5"},{"price":1006.01,"quantity":0.87,"orderId":"2grfftl65t5fwgplpovpku","filled":0.69,"side":"buy","userId":"5"},{"price":1006.08,"quantity":0.87,"orderId":"og98vcosw9pytipsnbqrz","filled":0,"side":"buy","userId":"5"},{"price":1006.09,"quantity":1.31,"orderId":"739ktuqxrokbiw8i99s9u5","filled":0,"side":"buy","userId":"5"},{"price":1007.02,"quantity":2.21,"orderId":"empb1umhpr1vndnm6c2pz","filled":0.7199999999999999,"side":"buy","userId":"5"}],"asks":[{"price":1009.62,"quantity":1.03,"orderId":"zcl8hbu1duispyanofefsr","filled":0,"side":"sell","userId":"5"},{"price":1010.08,"quantity":0.55,"orderId":"ctv6d8dj6ui2x35b46m9ed","filled":0,"side":"sell","userId":"5"},{"price":1010.18,"quantity":2.18,"orderId":"qbn8fereiyrhcr4xknpqj","filled":0,"side":"sell","userId":"5"},{"price":1010.49,"quantity":0.72,"orderId":"04nxqtyx4wa47ambc11v4ee","filled":0,"side":"sell","userId":"5"},{"price":1010.72,"quantity":1.08,"orderId":"iv9r8kkmur66sxqq4vppn","filled":0,"side":"sell","userId":"5"},{"price":1011.71,"quantity":2.38,"orderId":"77pja6y459qa97lfi00lw9","filled":0,"side":"sell","userId":"5"},{"price":1012.95,"quantity":1.51,"orderId":"e84gas1mjkwufn5wj18ub","filled":0,"side":"sell","userId":"5"},{"price":1013.19,"quantity":2.03,"orderId":"ulhgfsahzgf2yios3g2083","filled":0,"side":"sell","userId":"5"}],"lastTradeId":61831,"currentPrice":1007.2}],"balances":[["1",{"INR":{"available":999999999999999,"locked":0},"TATA":{"available":999999999999999,"locked":0}}],["2",{"INR":{"available":1000000000010134,"locked":0},"TATA":{"available":999999999999983,"locked":6}}],["5",{"INR":{"available":999999999754213.2,"locked":236154.0462999993},"TATA":{"available":999999999999898.5,"locked":61.71999999999886}}]]}